tensorflow_cloud/__init__.py
tensorflow_cloud/version.py
tensorflow_cloud/core/__init__.py
tensorflow_cloud/core/containerize.py
tensorflow_cloud/core/deploy.py
tensorflow_cloud/core/docker_config.py
tensorflow_cloud/core/gcp.py
tensorflow_cloud/core/machine_config.py
tensorflow_cloud/core/preprocess.py
tensorflow_cloud/core/run.py
tensorflow_cloud/core/validate.py
tensorflow_cloud/core/tests/__init__.py
tensorflow_cloud/core/tests/unit/__init__.py
tensorflow_cloud/core/tests/unit/constants.py
tensorflow_cloud/core/tests/unit/containerize_test.py
tensorflow_cloud/core/tests/unit/deploy_test.py
tensorflow_cloud/core/tests/unit/docker_config_test.py
tensorflow_cloud/core/tests/unit/gcp_test.py
tensorflow_cloud/core/tests/unit/preprocess_test.py
tensorflow_cloud/core/tests/unit/validate_test.py
tensorflow_cloud/tuner/__init__.py
tensorflow_cloud/tuner/cloud_fit_client.py
tensorflow_cloud/tuner/cloud_fit_remote.py
tensorflow_cloud/tuner/cloud_fit_utils.py
tensorflow_cloud/tuner/constants.py
tensorflow_cloud/tuner/tuner.py
tensorflow_cloud/tuner/utils.py
tensorflow_cloud/tuner/vizier_client.py
tensorflow_cloud/tuner/vizier_client_interface.py
tensorflow_cloud/tuner/vizier_client_ucaip_interface.py
tensorflow_cloud/tuner/api/ml_public_google_rest_v1.json
tensorflow_cloud/utils/__init__.py
tensorflow_cloud/utils/google_api_client.py
tensorflow_cloud/utils/tf_utils.py
tensorflow_cloud-0.1.16.dist-info/METADATA
tensorflow_cloud-0.1.16.dist-info/WHEEL
tensorflow_cloud-0.1.16.dist-info/top_level.txt
tensorflow_cloud-0.1.16.dist-info/RECORD
